{
  "name": "Mollie Garcia",
  "age": 18,
  "address": {
    "street": "Dojij Grove",
    "city": "Vuizeli",
    "state": "MN",
    "zip": "88791"
  },
  "contact": {
    "phone": "(552) 958-7754",
    "servicePhone": "800414148"
  },
  "birthday": "1976-07-09T20:13:35.234Z",
  "ip": "230.225.205.198",
  "foo": "bar",
  "profile": {
    "about": "Umhehaca hisare mupriv koureha kekiti az eziilra ika pa fefsomot kuppuru iwozisa pikjim. Pejewirac wepezamu jupaw ho jedafeh ovdek sedi reguz wanalra vo opi odujo mebpognil. Gas caid sod pa hobiseko hih rolcod seabe samja kazoav julewi eggirpem jilogo nunohoro feduwsit luvebe. On mopsen fil milna pijzavgo at tudwe juczogpos okewa og mak ni culuto dohavamu. Elujo viogzu veloshet tikeboj ofzavrow agvih dehuma bun hi jijhu bolmo vip jeuwdu. Mub gi jis ku oko wuecabi oku igo hibu tul va nuvef no tulev. Gijute mog vevwijca leji tipo duc tes be dav wudu hovsaj ecuipnow zes.",
    "bio": "Zejovuz liluj bupofu fop jecdetom erzuh cicu uc wicuz ovuwi lorpen jed. Ivefanbe becu rega ajeano ajorohow va maf ef zeowiaz ho vumu nep buwaju gaf vimadna. Lawod mes siune ajcev tarsec ramkehsab cippep le neclob eve mawco ujemuw sojbi capewfa owe. Cab ma ec baz jebatos unu sisuj kodzauw taw bo genoco hug cub. Cocu la sihzuvav so dorwe zob zetzeznoj noupo sotoh gunuwi nolnehve ja cawi ro fifip."
  },
  "apiKey": "4dcc76f660226001d53bed25b92d93eb332630cd994b7728b6b64700300b3b56",
  "currency": {
    "code": "BGN",
    "name": "Bulgaria Lev"
  }
}