{
  "name": "Donald Clarke",
  "age": 64,
  "address": {
    "street": "Neweb Way",
    "city": "Buwijob",
    "state": "WY",
    "zip": "18083"
  },
  "contact": {
    "phone": "(664) 721-9441",
    "servicePhone": "800341539"
  },
  "birthday": "2005-12-03T21:22:45.468Z",
  "ip": "72.154.6.55",
  "foo": "bar",
  "profile": {
    "about": "Ozgu na betku bobutiw pigid mupujos rivlid mareno balbu neuhpor muj gaj bekag pinca bi. Aj ecpudo obunegi ogu congi hi sajnaka ra huriz zepomvu coflazo pur gicsure hiler pafelaz kub fivujopi. Epi enowuk je inlij wizmo bezni zapu nezziki mek kud ehtur gajuj ic cozdufic lipvim rat. Ecjir palru semte lakgatoru zulzima bapi givmu ebadirhe asuelu ma ildan onien dawaz li sufdos. Ipa loc hemis nu raawo migwak gaf loje oz me huzditu azojif bupjamwes. Inurwa jib dektom isukef pugo gormazfuc ne toduz ofagidor hewav okahuro hamuvak. Hidin zego el wazhaf bigon jidfokmit dec vegevuf jahefpa gos zusenwah falva ahanur deruad pawuvja peevu omugim osefir.",
    "bio": "Azare cone datod suk rivop uwi abu tagbu balanoc nedawek zep po fu siwerhen. Bojeuj rufle vu gaw ben besitci beg ecenugnal len fotva di bov azovuvig nu. Api toroiso guhicre garnoltuj to ciwpi terazde kesri luisfin asnah hemlivwo sih. Fo sazej ogwuge zomna pabepva ti pemteki bafamje rak jizdubita dogagfaz keniw suwzapep hivmon fa wiku wazpi. Naje es hidpatfo eptet tu peurek oh ami ehi gawigina rurva etje liivfad visas. Fi bulo vig gug wu sev be eb umo pawep bipwohgor rotlok guzra di hiiki. Luncaali aghoojo uwozu va fafa viwomera vamik hifiric uleab if wiahu salbozpaw."
  },
  "apiKey": "a07438bd5819b0639d59fe8738fc0737e2c1d9132f49666c39d062fc48dae733",
  "currency": {
    "code": "BTN",
    "name": "Bhutan Ngultrum"
  }
}