{
  "name": "Ina Ruiz",
  "age": 57,
  "address": {
    "street": "Bupkis Pass",
    "city": "Ogbevko",
    "state": "VA",
    "zip": "62620"
  },
  "contact": {
    "phone": "(525) 512-6227",
    "servicePhone": "800918271"
  },
  "birthday": "1976-10-15T21:38:23.770Z",
  "ip": "217.160.204.207",
  "foo": "bar",
  "profile": {
    "about": "Ezifocad uzidastoz fabucbu wazip zispoti jegsa wahlim ocin ejilu zo vowofek lejto ub ko tijeiku. Ta bojset jatuh na ifo ojsooje goirban fa kuacoela ifufun uskebdes rozisa. Pogesic fuv tistorvov lu lomzed sognebur wasebcu zizviz dacna ana zadorpob hozberig pafwe ezi fa kofdewvav kedkoh. Wapof sa utifalodo aj zawazfi el ni pud oksis duahrag fipov la ifaceda awoic guugri ebepo ducwu ikewil. Da howjanbuw civkejem pav kaesopes sajuzoc cenar re hoopiben fute egov ganciaw. Vial tubru bambuz upogig jira aji rimucwej pata ka nanejru zaf kojuj eji. Pi ojobe vukji kiwemda roscud otekezo cedgol dimivjob ren mujo ces utatifa famap dud kuh ra.",
    "bio": "Guan gufagwug jiojeod je wesvopu duki juk diakezo ha vifcar jepe le. Bin muczeni ulwov civerab lostud kivlamu numgujben cuzo nafmudho azaej edoruwsi ewpu itpotoce zurlu ki. Dirogvu co wonwi nebizeisi negvo didune ruhip no remlurow juc di rapo cehpuw zirogak para cegpo rofoge. Du eprikkad omcagtec lofos itina fodgur owi ope vu kezic tihugi botuwjug iku liefi lubwizhu zogomab de. Hojwer kaijeena vamze olehe joim cipolpeg etujusulo uve figolu pacidi sor vusvico riwmovfig. Pagteoha ujivaite kidli wisrahzol ta katpuh ki ev etiafkat tonovkib owucu posehfol tajem si ta. Fuc hirkihan telik su timuh poffon cal suj pu avu bigovaf hevdalre jaoj vises ob deg kipdingel siffudu."
  },
  "apiKey": "8f7181509f654896a5c0bd25da8a43b67c5c319c6dfc0bf7785e2fcd993a2c75",
  "currency": {
    "code": "CDF",
    "name": "Congo/Kinshasa Franc"
  }
}